[{"Date":"2022-01-24~2022-01-30","Amount":178811.0,"Tickets":794.0,"TotalAmount":178811.0,"TotalTickets":794,"Rate":0.0,"TheaterCount":13,"MovieId":"20374","Created_time":1738332227899,"updated_time":1738332227899},{"Date":"2022-01-31~2022-02-06","Amount":206409.0,"Tickets":898.0,"TotalAmount":385220.0,"TotalTickets":1692,"Rate":0.1543417351,"TheaterCount":13,"MovieId":"20374","Created_time":1738332227899,"updated_time":1738332227899},{"Date":"2022-02-07~2022-02-13","Amount":170167.0,"Tickets":752.0,"TotalAmount":555387.0,"TotalTickets":2444,"Rate":-0.175583429,"TheaterCount":13,"MovieId":"20374","Created_time":1738332227899,"updated_time":1738332227899},{"Date":"2022-02-14~2022-02-20","Amount":59220.0,"Tickets":261.0,"TotalAmount":614607.0,"TotalTickets":2705,"Rate":-0.6519889285,"TheaterCount":11,"MovieId":"20374","Created_time":1738332227899,"updated_time":1738332227899},{"Date":"2022-02-21~2022-02-27","Amount":3580.0,"Tickets":15.0,"TotalAmount":618187.0,"TotalTickets":2720,"Rate":-0.9395474502,"TheaterCount":2,"MovieId":"20374","Created_time":1738332227899,"updated_time":1738332227899},{"Date":"2022-02-28~2022-03-06","Amount":null,"Tickets":null,"TotalAmount":618187.0,"TotalTickets":2720,"Rate":-1.0,"TheaterCount":0,"MovieId":"20374","Created_time":1738332227899,"updated_time":1738332227899},{"Date":"2022-03-07~2022-03-13","Amount":null,"Tickets":null,"TotalAmount":618187.0,"TotalTickets":2720,"Rate":0.0,"TheaterCount":0,"MovieId":"20374","Created_time":1738332227899,"updated_time":1738332227899},{"Date":"2022-03-14~2022-03-20","Amount":null,"Tickets":null,"TotalAmount":618187.0,"TotalTickets":2720,"Rate":0.0,"TheaterCount":0,"MovieId":"20374","Created_time":1738332227899,"updated_time":1738332227899},{"Date":"2022-03-21~2022-03-27","Amount":null,"Tickets":null,"TotalAmount":618187.0,"TotalTickets":2720,"Rate":0.0,"TheaterCount":0,"MovieId":"20374","Created_time":1738332227899,"updated_time":1738332227899},{"Date":"2022-03-28~2022-04-03","Amount":null,"Tickets":null,"TotalAmount":618187.0,"TotalTickets":2720,"Rate":0.0,"TheaterCount":0,"MovieId":"20374","Created_time":1738332227899,"updated_time":1738332227899},{"Date":"2022-04-04~2022-04-10","Amount":null,"Tickets":null,"TotalAmount":618187.0,"TotalTickets":2720,"Rate":0.0,"TheaterCount":0,"MovieId":"20374","Created_time":1738332227899,"updated_time":1738332227899},{"Date":"2022-04-11~2022-04-17","Amount":null,"Tickets":null,"TotalAmount":618187.0,"TotalTickets":2720,"Rate":0.0,"TheaterCount":0,"MovieId":"20374","Created_time":1738332227899,"updated_time":1738332227899},{"Date":"2022-04-18~2022-04-24","Amount":null,"Tickets":null,"TotalAmount":618187.0,"TotalTickets":2720,"Rate":0.0,"TheaterCount":0,"MovieId":"20374","Created_time":1738332227899,"updated_time":1738332227899},{"Date":"2022-04-25~2022-05-01","Amount":null,"Tickets":null,"TotalAmount":618187.0,"TotalTickets":2720,"Rate":0.0,"TheaterCount":0,"MovieId":"20374","Created_time":1738332227899,"updated_time":1738332227899},{"Date":"2022-05-02~2022-05-08","Amount":null,"Tickets":null,"TotalAmount":618187.0,"TotalTickets":2720,"Rate":0.0,"TheaterCount":0,"MovieId":"20374","Created_time":1738332227899,"updated_time":1738332227899},{"Date":"2022-05-09~2022-05-15","Amount":null,"Tickets":null,"TotalAmount":618187.0,"TotalTickets":2720,"Rate":0.0,"TheaterCount":0,"MovieId":"20374","Created_time":1738332227899,"updated_time":1738332227899},{"Date":"2022-05-16~2022-05-22","Amount":null,"Tickets":null,"TotalAmount":618187.0,"TotalTickets":2720,"Rate":0.0,"TheaterCount":0,"MovieId":"20374","Created_time":1738332227899,"updated_time":1738332227899},{"Date":"2022-05-23~2022-05-29","Amount":null,"Tickets":null,"TotalAmount":618187.0,"TotalTickets":2720,"Rate":0.0,"TheaterCount":0,"MovieId":"20374","Created_time":1738332227899,"updated_time":1738332227899},{"Date":"2022-05-30~2022-06-05","Amount":null,"Tickets":null,"TotalAmount":618187.0,"TotalTickets":2720,"Rate":0.0,"TheaterCount":0,"MovieId":"20374","Created_time":1738332227899,"updated_time":1738332227899},{"Date":"2022-06-06~2022-06-12","Amount":null,"Tickets":null,"TotalAmount":618187.0,"TotalTickets":2720,"Rate":0.0,"TheaterCount":0,"MovieId":"20374","Created_time":1738332227899,"updated_time":1738332227899},{"Date":"2022-06-13~2022-06-19","Amount":null,"Tickets":null,"TotalAmount":618187.0,"TotalTickets":2720,"Rate":0.0,"TheaterCount":0,"MovieId":"20374","Created_time":1738332227899,"updated_time":1738332227899},{"Date":"2022-06-20~2022-06-26","Amount":null,"Tickets":null,"TotalAmount":618187.0,"TotalTickets":2720,"Rate":0.0,"TheaterCount":0,"MovieId":"20374","Created_time":1738332227899,"updated_time":1738332227899},{"Date":"2022-06-27~2022-07-03","Amount":null,"Tickets":null,"TotalAmount":618187.0,"TotalTickets":2720,"Rate":0.0,"TheaterCount":0,"MovieId":"20374","Created_time":1738332227899,"updated_time":1738332227899},{"Date":"2022-07-04~2022-07-10","Amount":null,"Tickets":null,"TotalAmount":618187.0,"TotalTickets":2720,"Rate":0.0,"TheaterCount":0,"MovieId":"20374","Created_time":1738332227899,"updated_time":1738332227899},{"Date":"2022-07-11~2022-07-17","Amount":null,"Tickets":null,"TotalAmount":618187.0,"TotalTickets":2720,"Rate":0.0,"TheaterCount":0,"MovieId":"20374","Created_time":1738332227899,"updated_time":1738332227899},{"Date":"2022-07-18~2022-07-24","Amount":null,"Tickets":null,"TotalAmount":618187.0,"TotalTickets":2720,"Rate":0.0,"TheaterCount":0,"MovieId":"20374","Created_time":1738332227899,"updated_time":1738332227899},{"Date":"2022-07-25~2022-07-31","Amount":null,"Tickets":null,"TotalAmount":618187.0,"TotalTickets":2720,"Rate":0.0,"TheaterCount":0,"MovieId":"20374","Created_time":1738332227899,"updated_time":1738332227899},{"Date":"2022-08-01~2022-08-07","Amount":null,"Tickets":null,"TotalAmount":618187.0,"TotalTickets":2720,"Rate":0.0,"TheaterCount":0,"MovieId":"20374","Created_time":1738332227899,"updated_time":1738332227899},{"Date":"2022-08-08~2022-08-14","Amount":null,"Tickets":null,"TotalAmount":618187.0,"TotalTickets":2720,"Rate":0.0,"TheaterCount":0,"MovieId":"20374","Created_time":1738332227899,"updated_time":1738332227899},{"Date":"2022-08-15~2022-08-21","Amount":null,"Tickets":null,"TotalAmount":618187.0,"TotalTickets":2720,"Rate":0.0,"TheaterCount":0,"MovieId":"20374","Created_time":1738332227899,"updated_time":1738332227899},{"Date":"2022-08-22~2022-08-28","Amount":null,"Tickets":null,"TotalAmount":618187.0,"TotalTickets":2720,"Rate":0.0,"TheaterCount":0,"MovieId":"20374","Created_time":1738332227899,"updated_time":1738332227899},{"Date":"2022-08-29~2022-09-04","Amount":null,"Tickets":null,"TotalAmount":618187.0,"TotalTickets":2720,"Rate":0.0,"TheaterCount":0,"MovieId":"20374","Created_time":1738332227899,"updated_time":1738332227899},{"Date":"2022-09-05~2022-09-11","Amount":null,"Tickets":null,"TotalAmount":618187.0,"TotalTickets":2720,"Rate":0.0,"TheaterCount":0,"MovieId":"20374","Created_time":1738332227899,"updated_time":1738332227899},{"Date":"2022-09-12~2022-09-18","Amount":null,"Tickets":null,"TotalAmount":618187.0,"TotalTickets":2720,"Rate":0.0,"TheaterCount":0,"MovieId":"20374","Created_time":1738332227899,"updated_time":1738332227899},{"Date":"2022-09-19~2022-09-25","Amount":null,"Tickets":null,"TotalAmount":618187.0,"TotalTickets":2720,"Rate":0.0,"TheaterCount":0,"MovieId":"20374","Created_time":1738332227899,"updated_time":1738332227899},{"Date":"2022-09-26~2022-10-02","Amount":null,"Tickets":null,"TotalAmount":618187.0,"TotalTickets":2720,"Rate":0.0,"TheaterCount":0,"MovieId":"20374","Created_time":1738332227899,"updated_time":1738332227899},{"Date":"2022-10-03~2022-10-09","Amount":null,"Tickets":null,"TotalAmount":618187.0,"TotalTickets":2720,"Rate":0.0,"TheaterCount":0,"MovieId":"20374","Created_time":1738332227899,"updated_time":1738332227899},{"Date":"2022-10-10~2022-10-16","Amount":null,"Tickets":null,"TotalAmount":618187.0,"TotalTickets":2720,"Rate":0.0,"TheaterCount":0,"MovieId":"20374","Created_time":1738332227899,"updated_time":1738332227899},{"Date":"2022-10-17~2022-10-23","Amount":null,"Tickets":null,"TotalAmount":618187.0,"TotalTickets":2720,"Rate":0.0,"TheaterCount":0,"MovieId":"20374","Created_time":1738332227899,"updated_time":1738332227899},{"Date":"2022-10-24~2022-10-30","Amount":null,"Tickets":null,"TotalAmount":618187.0,"TotalTickets":2720,"Rate":0.0,"TheaterCount":0,"MovieId":"20374","Created_time":1738332227899,"updated_time":1738332227899},{"Date":"2022-10-31~2022-11-06","Amount":null,"Tickets":null,"TotalAmount":618187.0,"TotalTickets":2720,"Rate":0.0,"TheaterCount":0,"MovieId":"20374","Created_time":1738332227899,"updated_time":1738332227899},{"Date":"2022-11-07~2022-11-13","Amount":null,"Tickets":null,"TotalAmount":618187.0,"TotalTickets":2720,"Rate":0.0,"TheaterCount":0,"MovieId":"20374","Created_time":1738332227899,"updated_time":1738332227899},{"Date":"2022-11-14~2022-11-20","Amount":null,"Tickets":null,"TotalAmount":618187.0,"TotalTickets":2720,"Rate":0.0,"TheaterCount":0,"MovieId":"20374","Created_time":1738332227899,"updated_time":1738332227899},{"Date":"2022-11-21~2022-11-27","Amount":null,"Tickets":null,"TotalAmount":618187.0,"TotalTickets":2720,"Rate":0.0,"TheaterCount":0,"MovieId":"20374","Created_time":1738332227899,"updated_time":1738332227899},{"Date":"2022-11-28~2022-12-04","Amount":null,"Tickets":null,"TotalAmount":618187.0,"TotalTickets":2720,"Rate":0.0,"TheaterCount":0,"MovieId":"20374","Created_time":1738332227899,"updated_time":1738332227899},{"Date":"2022-12-05~2022-12-11","Amount":null,"Tickets":null,"TotalAmount":618187.0,"TotalTickets":2720,"Rate":0.0,"TheaterCount":0,"MovieId":"20374","Created_time":1738332227899,"updated_time":1738332227899},{"Date":"2022-12-12~2022-12-18","Amount":null,"Tickets":null,"TotalAmount":618187.0,"TotalTickets":2720,"Rate":0.0,"TheaterCount":0,"MovieId":"20374","Created_time":1738332227899,"updated_time":1738332227899},{"Date":"2022-12-19~2022-12-25","Amount":null,"Tickets":null,"TotalAmount":618187.0,"TotalTickets":2720,"Rate":0.0,"TheaterCount":0,"MovieId":"20374","Created_time":1738332227899,"updated_time":1738332227899},{"Date":"2022-12-26~2023-01-01","Amount":null,"Tickets":null,"TotalAmount":618187.0,"TotalTickets":2720,"Rate":0.0,"TheaterCount":0,"MovieId":"20374","Created_time":1738332227899,"updated_time":1738332227899},{"Date":"2023-01-02~2023-01-08","Amount":null,"Tickets":null,"TotalAmount":618187.0,"TotalTickets":2720,"Rate":0.0,"TheaterCount":0,"MovieId":"20374","Created_time":1738332227899,"updated_time":1738332227899},{"Date":"2023-01-09~2023-01-15","Amount":28250.0,"Tickets":113.0,"TotalAmount":646437.0,"TotalTickets":2833,"Rate":0.0,"TheaterCount":1,"MovieId":"20374","Created_time":1738332227899,"updated_time":1738332227899},{"Date":"2023-01-16~2023-01-22","Amount":null,"Tickets":null,"TotalAmount":646437.0,"TotalTickets":2833,"Rate":-1.0,"TheaterCount":0,"MovieId":"20374","Created_time":1738332227899,"updated_time":1738332227899},{"Date":"2023-01-23~2023-01-29","Amount":null,"Tickets":null,"TotalAmount":646437.0,"TotalTickets":2833,"Rate":0.0,"TheaterCount":0,"MovieId":"20374","Created_time":1738332227899,"updated_time":1738332227899},{"Date":"2023-01-30~2023-02-05","Amount":null,"Tickets":null,"TotalAmount":646437.0,"TotalTickets":2833,"Rate":0.0,"TheaterCount":0,"MovieId":"20374","Created_time":1738332227899,"updated_time":1738332227899},{"Date":"2023-02-06~2023-02-12","Amount":null,"Tickets":null,"TotalAmount":646437.0,"TotalTickets":2833,"Rate":0.0,"TheaterCount":0,"MovieId":"20374","Created_time":1738332227899,"updated_time":1738332227899},{"Date":"2023-02-13~2023-02-19","Amount":null,"Tickets":null,"TotalAmount":646437.0,"TotalTickets":2833,"Rate":0.0,"TheaterCount":0,"MovieId":"20374","Created_time":1738332227899,"updated_time":1738332227899},{"Date":"2023-02-20~2023-02-26","Amount":null,"Tickets":null,"TotalAmount":646437.0,"TotalTickets":2833,"Rate":0.0,"TheaterCount":0,"MovieId":"20374","Created_time":1738332227899,"updated_time":1738332227899},{"Date":"2023-02-27~2023-03-05","Amount":null,"Tickets":null,"TotalAmount":646437.0,"TotalTickets":2833,"Rate":0.0,"TheaterCount":0,"MovieId":"20374","Created_time":1738332227899,"updated_time":1738332227899},{"Date":"2023-03-06~2023-03-12","Amount":null,"Tickets":null,"TotalAmount":646437.0,"TotalTickets":2833,"Rate":0.0,"TheaterCount":0,"MovieId":"20374","Created_time":1738332227899,"updated_time":1738332227899},{"Date":"2023-03-13~2023-03-19","Amount":null,"Tickets":null,"TotalAmount":646437.0,"TotalTickets":2833,"Rate":0.0,"TheaterCount":0,"MovieId":"20374","Created_time":1738332227899,"updated_time":1738332227899},{"Date":"2023-03-20~2023-03-26","Amount":null,"Tickets":null,"TotalAmount":646437.0,"TotalTickets":2833,"Rate":0.0,"TheaterCount":0,"MovieId":"20374","Created_time":1738332227899,"updated_time":1738332227899},{"Date":"2023-03-27~2023-04-02","Amount":null,"Tickets":null,"TotalAmount":646437.0,"TotalTickets":2833,"Rate":0.0,"TheaterCount":0,"MovieId":"20374","Created_time":1738332227899,"updated_time":1738332227899},{"Date":"2023-04-03~2023-04-09","Amount":null,"Tickets":null,"TotalAmount":646437.0,"TotalTickets":2833,"Rate":0.0,"TheaterCount":0,"MovieId":"20374","Created_time":1738332227899,"updated_time":1738332227899},{"Date":"2023-04-10~2023-04-16","Amount":null,"Tickets":null,"TotalAmount":646437.0,"TotalTickets":2833,"Rate":0.0,"TheaterCount":0,"MovieId":"20374","Created_time":1738332227899,"updated_time":1738332227899},{"Date":"2023-04-17~2023-04-23","Amount":null,"Tickets":null,"TotalAmount":646437.0,"TotalTickets":2833,"Rate":0.0,"TheaterCount":0,"MovieId":"20374","Created_time":1738332227899,"updated_time":1738332227899},{"Date":"2023-04-24~2023-04-30","Amount":1125.0,"Tickets":6.0,"TotalAmount":647562.0,"TotalTickets":2839,"Rate":0.0,"TheaterCount":1,"MovieId":"20374","Created_time":1738332227899,"updated_time":1738332227899},{"Date":"2023-05-01~2023-05-07","Amount":null,"Tickets":null,"TotalAmount":647562.0,"TotalTickets":2839,"Rate":-1.0,"TheaterCount":0,"MovieId":"20374","Created_time":1738332227899,"updated_time":1738332227899},{"Date":"2023-05-08~2023-05-14","Amount":null,"Tickets":null,"TotalAmount":647562.0,"TotalTickets":2839,"Rate":0.0,"TheaterCount":0,"MovieId":"20374","Created_time":1738332227899,"updated_time":1738332227899},{"Date":"2023-05-15~2023-05-21","Amount":950.0,"Tickets":5.0,"TotalAmount":648512.0,"TotalTickets":2844,"Rate":0.0,"TheaterCount":1,"MovieId":"20374","Created_time":1738332227899,"updated_time":1738332227899},{"Date":"2023-05-22~2023-05-28","Amount":null,"Tickets":null,"TotalAmount":648512.0,"TotalTickets":2844,"Rate":-1.0,"TheaterCount":0,"MovieId":"20374","Created_time":1738332227899,"updated_time":1738332227899},{"Date":"2023-05-29~2023-06-04","Amount":null,"Tickets":null,"TotalAmount":648512.0,"TotalTickets":2844,"Rate":0.0,"TheaterCount":0,"MovieId":"20374","Created_time":1738332227899,"updated_time":1738332227899},{"Date":"2023-06-05~2023-06-11","Amount":null,"Tickets":null,"TotalAmount":648512.0,"TotalTickets":2844,"Rate":0.0,"TheaterCount":0,"MovieId":"20374","Created_time":1738332227899,"updated_time":1738332227899},{"Date":"2023-06-12~2023-06-18","Amount":null,"Tickets":null,"TotalAmount":648512.0,"TotalTickets":2844,"Rate":0.0,"TheaterCount":0,"MovieId":"20374","Created_time":1738332227899,"updated_time":1738332227899},{"Date":"2023-06-19~2023-06-25","Amount":null,"Tickets":null,"TotalAmount":648512.0,"TotalTickets":2844,"Rate":0.0,"TheaterCount":0,"MovieId":"20374","Created_time":1738332227899,"updated_time":1738332227899},{"Date":"2023-06-26~2023-07-02","Amount":null,"Tickets":null,"TotalAmount":648512.0,"TotalTickets":2844,"Rate":0.0,"TheaterCount":0,"MovieId":"20374","Created_time":1738332227899,"updated_time":1738332227899},{"Date":"2023-07-03~2023-07-09","Amount":null,"Tickets":null,"TotalAmount":648512.0,"TotalTickets":2844,"Rate":0.0,"TheaterCount":0,"MovieId":"20374","Created_time":1738332227899,"updated_time":1738332227899},{"Date":"2023-07-10~2023-07-16","Amount":null,"Tickets":null,"TotalAmount":648512.0,"TotalTickets":2844,"Rate":0.0,"TheaterCount":0,"MovieId":"20374","Created_time":1738332227899,"updated_time":1738332227899},{"Date":"2023-07-17~2023-07-23","Amount":null,"Tickets":null,"TotalAmount":648512.0,"TotalTickets":2844,"Rate":0.0,"TheaterCount":0,"MovieId":"20374","Created_time":1738332227899,"updated_time":1738332227899},{"Date":"2023-07-24~2023-07-30","Amount":null,"Tickets":null,"TotalAmount":648512.0,"TotalTickets":2844,"Rate":0.0,"TheaterCount":0,"MovieId":"20374","Created_time":1738332227899,"updated_time":1738332227899},{"Date":"2023-07-31~2023-08-06","Amount":null,"Tickets":null,"TotalAmount":648512.0,"TotalTickets":2844,"Rate":0.0,"TheaterCount":0,"MovieId":"20374","Created_time":1738332227899,"updated_time":1738332227899},{"Date":"2023-08-07~2023-08-13","Amount":250.0,"Tickets":1.0,"TotalAmount":648762.0,"TotalTickets":2845,"Rate":0.0,"TheaterCount":1,"MovieId":"20374","Created_time":1738332227899,"updated_time":1738332227899},{"Date":"2023-08-14~2023-08-20","Amount":37610.0,"Tickets":159.0,"TotalAmount":686372.0,"TotalTickets":3004,"Rate":149.44,"TheaterCount":5,"MovieId":"20374","Created_time":1738332227899,"updated_time":1738332227899},{"Date":"2023-08-21~2023-08-27","Amount":9535.0,"Tickets":39.0,"TotalAmount":695907.0,"TotalTickets":3043,"Rate":-0.7464770008,"TheaterCount":4,"MovieId":"20374","Created_time":1738332227899,"updated_time":1738332227899},{"Date":"2023-08-28~2023-09-03","Amount":3430.0,"Tickets":14.0,"TotalAmount":699337.0,"TotalTickets":3057,"Rate":-0.6402726796,"TheaterCount":1,"MovieId":"20374","Created_time":1738332227899,"updated_time":1738332227899},{"Date":"2023-09-04~2023-09-10","Amount":930.0,"Tickets":3.0,"TotalAmount":700267.0,"TotalTickets":3060,"Rate":-0.7288629738,"TheaterCount":1,"MovieId":"20374","Created_time":1738332227899,"updated_time":1738332227899}]