[{"Date":"2022-02-14~2022-02-20","Amount":2840.0,"Tickets":5.0,"TotalAmount":2840.0,"TotalTickets":5,"Rate":0.0,"TheaterCount":2,"MovieId":"20519","Created_time":1738332222052,"updated_time":1738332222052},{"Date":"2022-02-21~2022-02-27","Amount":9560.0,"Tickets":13.0,"TotalAmount":12400.0,"TotalTickets":18,"Rate":2.3661971831,"TheaterCount":2,"MovieId":"20519","Created_time":1738332222052,"updated_time":1738332222052},{"Date":"2022-02-28~2022-03-06","Amount":5080.0,"Tickets":8.0,"TotalAmount":17480.0,"TotalTickets":26,"Rate":-0.4686192469,"TheaterCount":2,"MovieId":"20519","Created_time":1738332222052,"updated_time":1738332222052},{"Date":"2022-03-07~2022-03-13","Amount":17530.0,"Tickets":27.0,"TotalAmount":35010.0,"TotalTickets":53,"Rate":2.4507874016,"TheaterCount":5,"MovieId":"20519","Created_time":1738332222052,"updated_time":1738332222052},{"Date":"2022-03-14~2022-03-20","Amount":null,"Tickets":null,"TotalAmount":35010.0,"TotalTickets":53,"Rate":-1.0,"TheaterCount":0,"MovieId":"20519","Created_time":1738332222052,"updated_time":1738332222052},{"Date":"2022-03-21~2022-03-27","Amount":26120.0,"Tickets":39.0,"TotalAmount":61130.0,"TotalTickets":92,"Rate":0.0,"TheaterCount":2,"MovieId":"20519","Created_time":1738332222052,"updated_time":1738332222052},{"Date":"2022-03-28~2022-04-03","Amount":1400.0,"Tickets":2.0,"TotalAmount":62530.0,"TotalTickets":94,"Rate":-0.9464012251,"TheaterCount":1,"MovieId":"20519","Created_time":1738332222052,"updated_time":1738332222052},{"Date":"2022-04-04~2022-04-10","Amount":4320.0,"Tickets":7.0,"TotalAmount":66850.0,"TotalTickets":101,"Rate":2.0857142857,"TheaterCount":2,"MovieId":"20519","Created_time":1738332222052,"updated_time":1738332222052},{"Date":"2022-04-11~2022-04-17","Amount":11480.0,"Tickets":17.0,"TotalAmount":78330.0,"TotalTickets":118,"Rate":1.6574074074,"TheaterCount":4,"MovieId":"20519","Created_time":1738332222052,"updated_time":1738332222052}]