[{"Date":"2022-03-14~2022-03-20","Amount":153959.0,"Tickets":653.0,"TotalAmount":153959.0,"TotalTickets":653,"Rate":0.0,"TheaterCount":23,"MovieId":"20681","Created_time":1738332224154,"updated_time":1738332224154},{"Date":"2022-03-21~2022-03-27","Amount":121481.0,"Tickets":525.0,"TotalAmount":275440.0,"TotalTickets":1178,"Rate":-0.2109522665,"TheaterCount":22,"MovieId":"20681","Created_time":1738332224154,"updated_time":1738332224154},{"Date":"2022-03-28~2022-04-03","Amount":9805.0,"Tickets":47.0,"TotalAmount":285245.0,"TotalTickets":1225,"Rate":-0.9192877899,"TheaterCount":11,"MovieId":"20681","Created_time":1738332224154,"updated_time":1738332224154},{"Date":"2022-04-04~2022-04-10","Amount":null,"Tickets":null,"TotalAmount":285245.0,"TotalTickets":1225,"Rate":-1.0,"TheaterCount":0,"MovieId":"20681","Created_time":1738332224154,"updated_time":1738332224154},{"Date":"2022-04-11~2022-04-17","Amount":null,"Tickets":null,"TotalAmount":285245.0,"TotalTickets":1225,"Rate":0.0,"TheaterCount":0,"MovieId":"20681","Created_time":1738332224154,"updated_time":1738332224154},{"Date":"2022-04-18~2022-04-24","Amount":null,"Tickets":null,"TotalAmount":285245.0,"TotalTickets":1225,"Rate":0.0,"TheaterCount":0,"MovieId":"20681","Created_time":1738332224154,"updated_time":1738332224154},{"Date":"2022-04-25~2022-05-01","Amount":6110.0,"Tickets":53.0,"TotalAmount":291355.0,"TotalTickets":1278,"Rate":0.0,"TheaterCount":2,"MovieId":"20681","Created_time":1738332224154,"updated_time":1738332224154},{"Date":"2022-05-02~2022-05-08","Amount":14240.0,"Tickets":120.0,"TotalAmount":305595.0,"TotalTickets":1398,"Rate":1.3306055646,"TheaterCount":2,"MovieId":"20681","Created_time":1738332224154,"updated_time":1738332224154},{"Date":"2022-05-09~2022-05-15","Amount":8400.0,"Tickets":79.0,"TotalAmount":313995.0,"TotalTickets":1477,"Rate":-0.4101123596,"TheaterCount":2,"MovieId":"20681","Created_time":1738332224154,"updated_time":1738332224154},{"Date":"2022-05-16~2022-05-22","Amount":4100.0,"Tickets":37.0,"TotalAmount":318095.0,"TotalTickets":1514,"Rate":-0.5119047619,"TheaterCount":2,"MovieId":"20681","Created_time":1738332224154,"updated_time":1738332224154},{"Date":"2022-05-23~2022-05-29","Amount":null,"Tickets":null,"TotalAmount":318095.0,"TotalTickets":1514,"Rate":-1.0,"TheaterCount":0,"MovieId":"20681","Created_time":1738332224154,"updated_time":1738332224154},{"Date":"2022-05-30~2022-06-05","Amount":4510.0,"Tickets":82.0,"TotalAmount":322605.0,"TotalTickets":1596,"Rate":0.0,"TheaterCount":1,"MovieId":"20681","Created_time":1738332224154,"updated_time":1738332224154},{"Date":"2022-06-06~2022-06-12","Amount":5005.0,"Tickets":91.0,"TotalAmount":327610.0,"TotalTickets":1687,"Rate":0.1097560976,"TheaterCount":1,"MovieId":"20681","Created_time":1738332224154,"updated_time":1738332224154},{"Date":"2022-06-13~2022-06-19","Amount":4840.0,"Tickets":88.0,"TotalAmount":332450.0,"TotalTickets":1775,"Rate":-0.032967033,"TheaterCount":1,"MovieId":"20681","Created_time":1738332224154,"updated_time":1738332224154},{"Date":"2022-06-20~2022-06-26","Amount":2255.0,"Tickets":41.0,"TotalAmount":334705.0,"TotalTickets":1816,"Rate":-0.5340909091,"TheaterCount":1,"MovieId":"20681","Created_time":1738332224154,"updated_time":1738332224154},{"Date":"2022-06-27~2022-07-03","Amount":null,"Tickets":null,"TotalAmount":334705.0,"TotalTickets":1816,"Rate":-1.0,"TheaterCount":0,"MovieId":"20681","Created_time":1738332224154,"updated_time":1738332224154},{"Date":"2022-07-04~2022-07-10","Amount":null,"Tickets":null,"TotalAmount":334705.0,"TotalTickets":1816,"Rate":0.0,"TheaterCount":0,"MovieId":"20681","Created_time":1738332224154,"updated_time":1738332224154},{"Date":"2022-07-11~2022-07-17","Amount":null,"Tickets":null,"TotalAmount":334705.0,"TotalTickets":1816,"Rate":0.0,"TheaterCount":0,"MovieId":"20681","Created_time":1738332224154,"updated_time":1738332224154},{"Date":"2022-07-18~2022-07-24","Amount":null,"Tickets":null,"TotalAmount":334705.0,"TotalTickets":1816,"Rate":0.0,"TheaterCount":0,"MovieId":"20681","Created_time":1738332224154,"updated_time":1738332224154},{"Date":"2022-07-25~2022-07-31","Amount":null,"Tickets":null,"TotalAmount":334705.0,"TotalTickets":1816,"Rate":0.0,"TheaterCount":0,"MovieId":"20681","Created_time":1738332224154,"updated_time":1738332224154},{"Date":"2022-08-01~2022-08-07","Amount":10072.0,"Tickets":86.0,"TotalAmount":344777.0,"TotalTickets":1902,"Rate":0.0,"TheaterCount":1,"MovieId":"20681","Created_time":1738332224154,"updated_time":1738332224154},{"Date":"2022-08-08~2022-08-14","Amount":13644.0,"Tickets":112.0,"TotalAmount":358421.0,"TotalTickets":2014,"Rate":0.3546465449,"TheaterCount":1,"MovieId":"20681","Created_time":1738332224154,"updated_time":1738332224154},{"Date":"2022-08-15~2022-08-21","Amount":3844.0,"Tickets":32.0,"TotalAmount":362265.0,"TotalTickets":2046,"Rate":-0.7182644386,"TheaterCount":1,"MovieId":"20681","Created_time":1738332224154,"updated_time":1738332224154}]