[{"Date":"2022-04-11~2022-04-17","Amount":55904.0,"Tickets":243,"TotalAmount":55904.0,"TotalTickets":243,"Rate":0.0,"TheaterCount":15,"MovieId":"20699","Created_time":1738332228712,"updated_time":1738332228712},{"Date":"2022-04-18~2022-04-24","Amount":48952.0,"Tickets":219,"TotalAmount":104856.0,"TotalTickets":462,"Rate":-0.1243560389,"TheaterCount":15,"MovieId":"20699","Created_time":1738332228712,"updated_time":1738332228712},{"Date":"2022-04-25~2022-05-01","Amount":6985.0,"Tickets":34,"TotalAmount":111841.0,"TotalTickets":496,"Rate":-0.8573092008,"TheaterCount":8,"MovieId":"20699","Created_time":1738332228712,"updated_time":1738332228712},{"Date":"2022-05-02~2022-05-08","Amount":1540.0,"Tickets":7,"TotalAmount":113381.0,"TotalTickets":503,"Rate":-0.7795275591,"TheaterCount":1,"MovieId":"20699","Created_time":1738332228712,"updated_time":1738332228712}]