[{"Date":"2022-10-10~2022-10-16","Amount":59633.0,"Tickets":249,"TotalAmount":59633.0,"TotalTickets":249,"Rate":0.0,"TheaterCount":16,"MovieId":"21862","Created_time":1738332225717,"updated_time":1738332225717},{"Date":"2022-10-17~2022-10-23","Amount":68716.0,"Tickets":300,"TotalAmount":128349.0,"TotalTickets":549,"Rate":0.1523149934,"TheaterCount":16,"MovieId":"21862","Created_time":1738332225717,"updated_time":1738332225717},{"Date":"2022-10-24~2022-10-30","Amount":19160.0,"Tickets":83,"TotalAmount":147509.0,"TotalTickets":632,"Rate":-0.7211711974,"TheaterCount":7,"MovieId":"21862","Created_time":1738332225717,"updated_time":1738332225717},{"Date":"2022-10-31~2022-11-06","Amount":1050.0,"Tickets":5,"TotalAmount":148559.0,"TotalTickets":637,"Rate":-0.9451983299,"TheaterCount":2,"MovieId":"21862","Created_time":1738332225717,"updated_time":1738332225717},{"Date":"2022-11-07~2022-11-13","Amount":23000.0,"Tickets":100,"TotalAmount":171559.0,"TotalTickets":737,"Rate":20.9047619048,"TheaterCount":1,"MovieId":"21862","Created_time":1738332225717,"updated_time":1738332225717}]