[{"Date":"2023-05-01~2023-05-07","Amount":31680.0,"Tickets":137,"TotalAmount":65537.0,"TotalTickets":282,"Rate":-0.0642998494,"TheaterCount":12,"MovieId":"24108","Created_time":1738332272993,"updated_time":1738332272993},{"Date":"2023-05-08~2023-05-14","Amount":3160.0,"Tickets":15,"TotalAmount":68697.0,"TotalTickets":297,"Rate":-0.9002525253,"TheaterCount":4,"MovieId":"24108","Created_time":1738332272993,"updated_time":1738332272993},{"Date":"2023-05-15~2023-05-21","Amount":920.0,"Tickets":4,"TotalAmount":69617.0,"TotalTickets":301,"Rate":-0.7088607595,"TheaterCount":2,"MovieId":"24108","Created_time":1738332272993,"updated_time":1738332272993},{"Date":"2023-05-22~2023-05-28","Amount":730.0,"Tickets":3,"TotalAmount":70347.0,"TotalTickets":304,"Rate":-0.2065217391,"TheaterCount":1,"MovieId":"24108","Created_time":1738332272993,"updated_time":1738332272993}]