[{"Date":"2023-12-11~2023-12-17","Amount":165628.0,"Tickets":670.0,"TotalAmount":409248.0,"TotalTickets":1535,"Rate":-0.3201379197,"TheaterCount":28,"MovieId":"26253","Created_time":1738332270081,"updated_time":1738332270081},{"Date":"2023-12-18~2023-12-24","Amount":100939.0,"Tickets":438.0,"TotalAmount":510187.0,"TotalTickets":1973,"Rate":-0.3905680199,"TheaterCount":27,"MovieId":"26253","Created_time":1738332270081,"updated_time":1738332270081},{"Date":"2023-12-25~2023-12-31","Amount":26420.0,"Tickets":116.0,"TotalAmount":536607.0,"TotalTickets":2089,"Rate":-0.7382577596,"TheaterCount":15,"MovieId":"26253","Created_time":1738332270081,"updated_time":1738332270081},{"Date":"2024-01-01~2024-01-07","Amount":2565.0,"Tickets":11.0,"TotalAmount":539172.0,"TotalTickets":2100,"Rate":-0.9029144587,"TheaterCount":3,"MovieId":"26253","Created_time":1738332270081,"updated_time":1738332270081},{"Date":"2024-01-08~2024-01-14","Amount":2490.0,"Tickets":10.0,"TotalAmount":541662.0,"TotalTickets":2110,"Rate":-0.0292397661,"TheaterCount":1,"MovieId":"26253","Created_time":1738332270081,"updated_time":1738332270081},{"Date":"2024-01-15~2024-01-21","Amount":null,"Tickets":null,"TotalAmount":541662.0,"TotalTickets":2110,"Rate":-1.0,"TheaterCount":0,"MovieId":"26253","Created_time":1738332270081,"updated_time":1738332270081},{"Date":"2024-01-22~2024-01-28","Amount":null,"Tickets":null,"TotalAmount":541662.0,"TotalTickets":2110,"Rate":0.0,"TheaterCount":0,"MovieId":"26253","Created_time":1738332270081,"updated_time":1738332270081},{"Date":"2024-01-29~2024-02-04","Amount":null,"Tickets":null,"TotalAmount":541662.0,"TotalTickets":2110,"Rate":0.0,"TheaterCount":0,"MovieId":"26253","Created_time":1738332270081,"updated_time":1738332270081},{"Date":"2024-02-05~2024-02-11","Amount":null,"Tickets":null,"TotalAmount":541662.0,"TotalTickets":2110,"Rate":0.0,"TheaterCount":0,"MovieId":"26253","Created_time":1738332270081,"updated_time":1738332270081},{"Date":"2024-02-12~2024-02-18","Amount":null,"Tickets":null,"TotalAmount":541662.0,"TotalTickets":2110,"Rate":0.0,"TheaterCount":0,"MovieId":"26253","Created_time":1738332270081,"updated_time":1738332270081},{"Date":"2024-02-19~2024-02-25","Amount":null,"Tickets":null,"TotalAmount":541662.0,"TotalTickets":2110,"Rate":0.0,"TheaterCount":0,"MovieId":"26253","Created_time":1738332270081,"updated_time":1738332270081},{"Date":"2024-02-26~2024-03-03","Amount":null,"Tickets":null,"TotalAmount":541662.0,"TotalTickets":2110,"Rate":0.0,"TheaterCount":0,"MovieId":"26253","Created_time":1738332270081,"updated_time":1738332270081},{"Date":"2024-03-04~2024-03-10","Amount":null,"Tickets":null,"TotalAmount":541662.0,"TotalTickets":2110,"Rate":0.0,"TheaterCount":0,"MovieId":"26253","Created_time":1738332270081,"updated_time":1738332270081},{"Date":"2024-03-11~2024-03-17","Amount":2887.0,"Tickets":23.0,"TotalAmount":544549.0,"TotalTickets":2133,"Rate":0.0,"TheaterCount":1,"MovieId":"26253","Created_time":1738332270081,"updated_time":1738332270081},{"Date":"2024-03-18~2024-03-24","Amount":3670.0,"Tickets":32.0,"TotalAmount":548219.0,"TotalTickets":2165,"Rate":0.2712157949,"TheaterCount":1,"MovieId":"26253","Created_time":1738332270081,"updated_time":1738332270081},{"Date":"2024-03-25~2024-03-31","Amount":900.0,"Tickets":8.0,"TotalAmount":549119.0,"TotalTickets":2173,"Rate":-0.7547683924,"TheaterCount":1,"MovieId":"26253","Created_time":1738332270081,"updated_time":1738332270081}]