[{"Date":"2024-03-11~2024-03-17","Amount":182970.0,"Tickets":805.0,"TotalAmount":467155.0,"TotalTickets":1998,"Rate":-0.3561588402,"TheaterCount":40,"MovieId":"26836","Created_time":1738332278853,"updated_time":1738332278853},{"Date":"2024-03-18~2024-03-24","Amount":54283.0,"Tickets":250.0,"TotalAmount":521438.0,"TotalTickets":2248,"Rate":-0.7033229491,"TheaterCount":18,"MovieId":"26836","Created_time":1738332278853,"updated_time":1738332278853},{"Date":"2024-03-25~2024-03-31","Amount":29185.0,"Tickets":133.0,"TotalAmount":550623.0,"TotalTickets":2381,"Rate":-0.4623546967,"TheaterCount":7,"MovieId":"26836","Created_time":1738332278853,"updated_time":1738332278853},{"Date":"2024-04-01~2024-04-07","Amount":24200.0,"Tickets":110.0,"TotalAmount":574823.0,"TotalTickets":2491,"Rate":-0.1708069214,"TheaterCount":1,"MovieId":"26836","Created_time":1738332278853,"updated_time":1738332278853},{"Date":"2024-04-08~2024-04-14","Amount":66660.0,"Tickets":293.0,"TotalAmount":641483.0,"TotalTickets":2784,"Rate":1.7545454545,"TheaterCount":3,"MovieId":"26836","Created_time":1738332278853,"updated_time":1738332278853},{"Date":"2024-04-15~2024-04-21","Amount":null,"Tickets":null,"TotalAmount":641483.0,"TotalTickets":2784,"Rate":-1.0,"TheaterCount":0,"MovieId":"26836","Created_time":1738332278853,"updated_time":1738332278853},{"Date":"2024-04-22~2024-04-28","Amount":null,"Tickets":null,"TotalAmount":641483.0,"TotalTickets":2784,"Rate":0.0,"TheaterCount":0,"MovieId":"26836","Created_time":1738332278853,"updated_time":1738332278853},{"Date":"2024-04-29~2024-05-05","Amount":null,"Tickets":null,"TotalAmount":641483.0,"TotalTickets":2784,"Rate":0.0,"TheaterCount":0,"MovieId":"26836","Created_time":1738332278853,"updated_time":1738332278853},{"Date":"2024-05-06~2024-05-12","Amount":null,"Tickets":null,"TotalAmount":641483.0,"TotalTickets":2784,"Rate":0.0,"TheaterCount":0,"MovieId":"26836","Created_time":1738332278853,"updated_time":1738332278853},{"Date":"2024-05-13~2024-05-19","Amount":null,"Tickets":null,"TotalAmount":641483.0,"TotalTickets":2784,"Rate":0.0,"TheaterCount":0,"MovieId":"26836","Created_time":1738332278853,"updated_time":1738332278853},{"Date":"2024-05-20~2024-05-26","Amount":null,"Tickets":null,"TotalAmount":641483.0,"TotalTickets":2784,"Rate":0.0,"TheaterCount":0,"MovieId":"26836","Created_time":1738332278853,"updated_time":1738332278853},{"Date":"2024-05-27~2024-06-02","Amount":3795.0,"Tickets":69.0,"TotalAmount":645278.0,"TotalTickets":2853,"Rate":0.0,"TheaterCount":1,"MovieId":"26836","Created_time":1738332278853,"updated_time":1738332278853},{"Date":"2024-06-03~2024-06-09","Amount":8415.0,"Tickets":153.0,"TotalAmount":653693.0,"TotalTickets":3006,"Rate":1.2173913043,"TheaterCount":1,"MovieId":"26836","Created_time":1738332278853,"updated_time":1738332278853},{"Date":"2024-06-10~2024-06-16","Amount":7755.0,"Tickets":141.0,"TotalAmount":661448.0,"TotalTickets":3147,"Rate":-0.0784313725,"TheaterCount":1,"MovieId":"26836","Created_time":1738332278853,"updated_time":1738332278853},{"Date":"2024-06-17~2024-06-23","Amount":3245.0,"Tickets":59.0,"TotalAmount":664693.0,"TotalTickets":3206,"Rate":-0.5815602837,"TheaterCount":1,"MovieId":"26836","Created_time":1738332278853,"updated_time":1738332278853}]